Metadata-Version: 2.1
Name: dsnd-probability-distributions-TajKaz
Version: 0.3
Summary: Gaussian distributions
Home-page: UNKNOWN
Author: Tajudeen Kazeem
Author-email: tajqas@gmail.com
License: UNKNOWN
Platform: UNKNOWN
